{
  "bcp_47_code": "glo",
  "iso_639_3_code": "glo",
  "glottocode": "gala1264",
  "wikidata_id": "Q2598797",
  "total_population": 25000,
  "language_scope": {
    "scope": "LANGUAGE",
    "source": "ISO_639"
  },
  "name_data": [
    {
      "name": "Galambu",
      "bcp_47_code": "en",
      "is_canonical": true,
      "source": "ISO_639"
    },
    {
      "name": "Kigalambu",
      "bcp_47_code": "sw",
      "is_canonical": true,
      "source": "WIKIDATA"
    },
    {
      "name": "Lenga Galambu",
      "bcp_47_code": "pms",
      "is_canonical": true,
      "source": "WIKIDATA"
    },
    {
      "name": "галамбу",
      "bcp_47_code": "ru",
      "is_canonical": true,
      "source": "WIKIDATA"
    },
    {
      "name": "galambu jezik",
      "bcp_47_code": "hr",
      "is_canonical": true,
      "source": "WIKIDATA"
    },
    {
      "name": "galamboueg",
      "bcp_47_code": "br",
      "is_canonical": true,
      "source": "WIKIDATA"
    },
    {
      "name": "Wikang Galambu",
      "bcp_47_code": "tl",
      "is_canonical": true,
      "source": "WIKIDATA"
    },
    {
      "name": "galambu",
      "bcp_47_code": "oc",
      "is_canonical": true,
      "source": "WIKIDATA"
    }
  ],
  "language_script_locale": [
    {
      "script": {
        "iso_15924_code": "latn",
        "is_canonical": true,
        "source": "WIKTIONARY"
      },
      "locale": {
        "iso_3166_code": "ng",
        "source": "GLOTTOLOG"
      },
      "speaker_data": {
        "number_of_speakers": 25000,
        "source": "WIKIPEDIA"
      },
      "geolocation": {
        "latitude": 10.1258,
        "longitude": 10.2542,
        "source": "GLOTTOLOG"
      }
    }
  ]
}