{
  "bcp_47_code": "hme",
  "iso_639_3_code": "hme",
  "macrolanguage_bcp_47_code": "hmn",
  "glottocode": "east2372",
  "wikidata_id": "Q12953559",
  "language_scope": {
    "scope": "LANGUAGE",
    "source": "ISO_639"
  },
  "language_description": {
    "description": "Hmongic language spoken by the Miao people in China",
    "source": "WIKIDATA"
  },
  "name_data": [
    {
      "name": "Eastern Huishui Hmong",
      "bcp_47_code": "en",
      "is_canonical": true,
      "source": "ISO_639"
    },
    {
      "name": "Eastern Huishui Miao",
      "bcp_47_code": "en",
      "source": "IETF"
    },
    {
      "name": "huishui oriental Lenga hmong",
      "bcp_47_code": "pms",
      "is_canonical": true,
      "source": "WIKIDATA"
    },
    {
      "name": "Kimiao ya Huishui ya Mashariki",
      "bcp_47_code": "sw",
      "is_canonical": true,
      "source": "WIKIDATA"
    },
    {
      "name": "huishui de l'est",
      "bcp_47_code": "fr",
      "is_canonical": true,
      "source": "WIKIDATA"
    }
  ],
  "language_script_locale": [
    {
      "script": {
        "iso_15924_code": "xxxx",
        "is_canonical": true,
        "source": "SOURCE_UNSPECIFIED"
      },
      "locale": {
        "iso_3166_code": "cn",
        "source": "GLOTTOLOG"
      }
    }
  ]
}