{
  "bcp_47_code": "maq",
  "iso_639_3_code": "maq",
  "glottocode": "chiq1250",
  "wikidata_id": "Q5101757",
  "total_population": 1500,
  "language_scope": {
    "scope": "LANGUAGE",
    "source": "ISO_639"
  },
  "name_data": [
    {
      "name": "Chiquihuitlán Mazatec",
      "bcp_47_code": "en",
      "is_canonical": true,
      "source": "ISO_639"
    },
    {
      "name": "чикиуитланский масатекский язык",
      "bcp_47_code": "ru",
      "is_canonical": true,
      "source": "WIKIDATA"
    },
    {
      "name": "Lenga mazatec",
      "bcp_47_code": "pms",
      "is_canonical": true,
      "source": "WIKIDATA"
    },
    {
      "name": "mazatekeg chiquihuitlán",
      "bcp_47_code": "br",
      "is_canonical": true,
      "source": "WIKIDATA"
    },
    {
      "name": "mazatèque de chiquihuitlan",
      "bcp_47_code": "fr",
      "is_canonical": true,
      "source": "WIKIDATA"
    },
    {
      "name": "língua chiquihuitlán mazatec",
      "bcp_47_code": "pt",
      "is_canonical": true,
      "source": "WIKIDATA"
    },
    {
      "name": "chiquihuitlán mazatec",
      "bcp_47_code": "sv",
      "is_canonical": true,
      "source": "WIKIDATA"
    },
    {
      "name": "Chiquihuitlan Mazatec",
      "bcp_47_code": "en",
      "source": "WIKIDATA"
    }
  ],
  "language_script_locale": [
    {
      "script": {
        "iso_15924_code": "latn",
        "is_canonical": true,
        "source": "GOOGLE_RESEARCH"
      },
      "locale": {
        "iso_3166_code": "mx",
        "source": "GOOGLE_RESEARCH"
      },
      "speaker_data": {
        "number_of_speakers": 1500,
        "source": "GOOGLE_RESEARCH"
      },
      "geolocation": {
        "latitude": 18.0541,
        "longitude": -96.6659,
        "source": "GLOTTOLOG"
      }
    }
  ]
}