{
  "bcp_47_code": "mcn",
  "iso_639_3_code": "mcn",
  "glottocode": "masa1322",
  "wikidata_id": "Q56668",
  "total_population": 230000,
  "language_scope": {
    "scope": "LANGUAGE",
    "source": "ISO_639"
  },
  "name_data": [
    {
      "name": "Masana",
      "bcp_47_code": "en",
      "is_canonical": true,
      "source": "ISO_639"
    },
    {
      "name": "Masa",
      "bcp_47_code": "de",
      "is_canonical": true,
      "source": "WIKIDATA"
    },
    {
      "name": "masana hizkuntza",
      "bcp_47_code": "eu",
      "is_canonical": true,
      "source": "WIKIDATA"
    },
    {
      "name": "masaneg",
      "bcp_47_code": "br",
      "is_canonical": true,
      "source": "WIKIDATA"
    },
    {
      "name": "масаски език",
      "bcp_47_code": "bg",
      "is_canonical": true,
      "source": "WIKIDATA"
    },
    {
      "name": "massa",
      "bcp_47_code": "fr",
      "is_canonical": true,
      "source": "WIKIDATA"
    },
    {
      "name": "Massa",
      "bcp_47_code": "en",
      "source": "WIKIDATA"
    },
    {
      "name": "masana jezik",
      "bcp_47_code": "hr",
      "is_canonical": true,
      "source": "WIKIDATA"
    },
    {
      "name": "llengua massa",
      "bcp_47_code": "ca",
      "is_canonical": true,
      "source": "WIKIDATA"
    },
    {
      "name": "Kimasana",
      "bcp_47_code": "sw",
      "is_canonical": true,
      "source": "WIKIDATA"
    },
    {
      "name": "Lenga Masana",
      "bcp_47_code": "pms",
      "is_canonical": true,
      "source": "WIKIDATA"
    },
    {
      "name": "Wikang Massa",
      "bcp_47_code": "tl",
      "is_canonical": true,
      "source": "WIKIDATA"
    },
    {
      "name": "масански јазик",
      "bcp_47_code": "mk",
      "is_canonical": true,
      "source": "WIKIDATA"
    },
    {
      "name": "Masa",
      "bcp_47_code": "nl",
      "is_canonical": true,
      "source": "WIKIDATA"
    },
    {
      "name": "língua massa",
      "bcp_47_code": "pt",
      "is_canonical": true,
      "source": "WIKIDATA"
    },
    {
      "name": "اللغة الماسية",
      "bcp_47_code": "ar",
      "is_canonical": true,
      "source": "WIKIDATA"
    },
    {
      "name": "masa",
      "bcp_47_code": "es",
      "is_canonical": true,
      "source": "WIKIDATA"
    },
    {
      "name": "massa",
      "bcp_47_code": "nb",
      "is_canonical": true,
      "source": "WIKIDATA"
    },
    {
      "name": "massa",
      "bcp_47_code": "mcn",
      "source": "WIKIDATA"
    },
    {
      "name": "Massa",
      "bcp_47_code": "ig",
      "is_canonical": true,
      "source": "WIKIDATA"
    },
    {
      "name": "маса",
      "bcp_47_code": "bg",
      "source": "WIKIDATA"
    },
    {
      "name": "langue masana",
      "bcp_47_code": "fr",
      "source": "WIKIDATA"
    },
    {
      "name": "langue masa",
      "bcp_47_code": "fr",
      "source": "WIKIDATA"
    },
    {
      "name": "masa",
      "bcp_47_code": "fr",
      "source": "WIKIDATA"
    },
    {
      "name": "Massa",
      "bcp_47_code": "mcn",
      "is_canonical": true,
      "source": "GOOGLE_RESEARCH"
    },
    {
      "name": "masa",
      "bcp_47_code": "mcn",
      "source": "WIKIDATA"
    },
    {
      "name": "masana",
      "bcp_47_code": "mcn",
      "source": "WIKIDATA"
    }
  ],
  "language_script_locale": [
    {
      "script": {
        "iso_15924_code": "latn",
        "is_canonical": true,
        "source": "GOOGLE_RESEARCH"
      },
      "locale": {
        "iso_3166_code": "td",
        "source": "GOOGLE_RESEARCH"
      },
      "speaker_data": {
        "number_of_speakers": 230000,
        "source": "GOOGLE_RESEARCH"
      },
      "geolocation": {
        "latitude": 10.120495,
        "longitude": 15.613914,
        "source": "GOOGLE_RESEARCH"
      }
    }
  ]
}