{
  "bcp_47_code": "mni",
  "iso_639_3_code": "mni",
  "glottocode": "mani1292",
  "wikidata_id": "Q33868",
  "total_population": 1500000,
  "language_scope": {
    "scope": "LANGUAGE",
    "source": "ISO_639"
  },
  "language_description": {
    "description": "Sino-Tibetan language",
    "source": "WIKIDATA"
  },
  "name_data": [
    {
      "name": "Manipuri",
      "bcp_47_code": "en",
      "source": "ISO_639"
    },
    {
      "name": "аманипур",
      "bcp_47_code": "ab",
      "is_canonical": true,
      "source": "CLDR"
    },
    {
      "name": "Manipuri",
      "bcp_47_code": "af",
      "is_canonical": true,
      "source": "CLDR"
    },
    {
      "name": "ማኒፑሪ",
      "bcp_47_code": "am",
      "is_canonical": true,
      "source": "CLDR"
    },
    {
      "name": "المانيبورية",
      "bcp_47_code": "ar",
      "is_canonical": true,
      "source": "CLDR"
    },
    {
      "name": "মণিপুৰী",
      "bcp_47_code": "as",
      "is_canonical": true,
      "source": "CLDR"
    },
    {
      "name": "manipuri",
      "bcp_47_code": "ast",
      "is_canonical": true,
      "source": "CLDR"
    },
    {
      "name": "manipüri",
      "bcp_47_code": "az",
      "iso_15924_code": "latn",
      "is_canonical": true,
      "source": "CLDR"
    },
    {
      "name": "мейтэй",
      "bcp_47_code": "be",
      "is_canonical": true,
      "source": "CLDR"
    },
    {
      "name": "манипурски",
      "bcp_47_code": "bg",
      "is_canonical": true,
      "source": "CLDR"
    },
    {
      "name": "مانیپوری",
      "bcp_47_code": "bgn",
      "is_canonical": true,
      "source": "CLDR"
    },
    {
      "name": "মণিপুরী",
      "bcp_47_code": "bn",
      "is_canonical": true,
      "source": "CLDR"
    },
    {
      "name": "manipuri",
      "bcp_47_code": "br",
      "is_canonical": true,
      "source": "CLDR"
    },
    {
      "name": "मनिपुरी",
      "bcp_47_code": "brx",
      "is_canonical": true,
      "source": "CLDR"
    },
    {
      "name": "manipuri",
      "bcp_47_code": "bs",
      "is_canonical": true,
      "source": "CLDR"
    },
    {
      "name": "manipurí",
      "bcp_47_code": "ca",
      "is_canonical": true,
      "source": "CLDR"
    },
    {
      "name": "𑄟𑄚𑄨𑄛𑄪𑄢𑄩",
      "bcp_47_code": "ccp",
      "is_canonical": true,
      "source": "CLDR"
    },
    {
      "name": "манипурийн",
      "bcp_47_code": "ce",
      "is_canonical": true,
      "source": "CLDR"
    },
    {
      "name": "ᎺᏂᏉᎵ",
      "bcp_47_code": "chr",
      "is_canonical": true,
      "source": "CLDR"
    },
    {
      "name": "مانیپووری",
      "bcp_47_code": "ckb",
      "is_canonical": true,
      "source": "CLDR"
    },
    {
      "name": "manipurština",
      "bcp_47_code": "cs",
      "is_canonical": true,
      "source": "CLDR"
    },
    {
      "name": "Manipwri",
      "bcp_47_code": "cy",
      "is_canonical": true,
      "source": "CLDR"
    },
    {
      "name": "manipuri",
      "bcp_47_code": "da",
      "is_canonical": true,
      "source": "CLDR"
    },
    {
      "name": "Meithei",
      "bcp_47_code": "de",
      "is_canonical": true,
      "source": "CLDR"
    },
    {
      "name": "manipuršćina",
      "bcp_47_code": "dsb",
      "is_canonical": true,
      "source": "CLDR"
    },
    {
      "name": "མ་ནི་པུ་རི",
      "bcp_47_code": "dz",
      "is_canonical": true,
      "source": "CLDR"
    },
    {
      "name": "Μανιπούρι",
      "bcp_47_code": "el",
      "is_canonical": true,
      "source": "CLDR"
    },
    {
      "name": "manipura",
      "bcp_47_code": "eo",
      "is_canonical": true,
      "source": "CLDR"
    },
    {
      "name": "manipurí",
      "bcp_47_code": "es",
      "is_canonical": true,
      "source": "CLDR"
    },
    {
      "name": "manipuri",
      "bcp_47_code": "et",
      "is_canonical": true,
      "source": "CLDR"
    },
    {
      "name": "manipurera",
      "bcp_47_code": "eu",
      "is_canonical": true,
      "source": "CLDR"
    },
    {
      "name": "مانیپوری",
      "bcp_47_code": "fa",
      "is_canonical": true,
      "source": "CLDR"
    },
    {
      "name": "manipuri",
      "bcp_47_code": "fi",
      "is_canonical": true,
      "source": "CLDR"
    },
    {
      "name": "Manipuri",
      "bcp_47_code": "fil",
      "is_canonical": true,
      "source": "CLDR"
    },
    {
      "name": "manupuri",
      "bcp_47_code": "fo",
      "is_canonical": true,
      "source": "CLDR"
    },
    {
      "name": "manipuri",
      "bcp_47_code": "fr",
      "is_canonical": true,
      "source": "CLDR"
    },
    {
      "name": "Manipoeri",
      "bcp_47_code": "fy",
      "is_canonical": true,
      "source": "CLDR"
    },
    {
      "name": "Manapúiris",
      "bcp_47_code": "ga",
      "is_canonical": true,
      "source": "CLDR"
    },
    {
      "name": "Manipuri",
      "bcp_47_code": "gd",
      "is_canonical": true,
      "source": "CLDR"
    },
    {
      "name": "manipuri",
      "bcp_47_code": "gl",
      "is_canonical": true,
      "source": "CLDR"
    },
    {
      "name": "Meithei-Schpraach",
      "bcp_47_code": "gsw",
      "is_canonical": true,
      "source": "CLDR"
    },
    {
      "name": "મણિપુરી",
      "bcp_47_code": "gu",
      "is_canonical": true,
      "source": "CLDR"
    },
    {
      "name": "Manipuri",
      "bcp_47_code": "ha",
      "is_canonical": true,
      "source": "CLDR"
    },
    {
      "name": "מניפורית",
      "bcp_47_code": "he",
      "is_canonical": true,
      "source": "CLDR"
    },
    {
      "name": "मणिपुरी",
      "bcp_47_code": "hi",
      "is_canonical": true,
      "source": "CLDR"
    },
    {
      "name": "manipurski",
      "bcp_47_code": "hr",
      "is_canonical": true,
      "source": "CLDR"
    },
    {
      "name": "manipuršćina",
      "bcp_47_code": "hsb",
      "is_canonical": true,
      "source": "CLDR"
    },
    {
      "name": "manipuri",
      "bcp_47_code": "hu",
      "is_canonical": true,
      "source": "CLDR"
    },
    {
      "name": "մանիպուրի",
      "bcp_47_code": "hy",
      "is_canonical": true,
      "source": "CLDR"
    },
    {
      "name": "manipuri",
      "bcp_47_code": "ia",
      "is_canonical": true,
      "source": "CLDR"
    },
    {
      "name": "Manipuri",
      "bcp_47_code": "id",
      "is_canonical": true,
      "source": "CLDR"
    },
    {
      "name": "Manịpụrị",
      "bcp_47_code": "ig",
      "is_canonical": true,
      "source": "CLDR"
    },
    {
      "name": "manípúrí",
      "bcp_47_code": "is",
      "is_canonical": true,
      "source": "CLDR"
    },
    {
      "name": "manipuri",
      "bcp_47_code": "it",
      "is_canonical": true,
      "source": "CLDR"
    },
    {
      "name": "マニプリ語",
      "bcp_47_code": "ja",
      "is_canonical": true,
      "source": "CLDR"
    },
    {
      "name": "Manipuri",
      "bcp_47_code": "jv",
      "is_canonical": true,
      "source": "CLDR"
    },
    {
      "name": "მანიპური",
      "bcp_47_code": "ka",
      "is_canonical": true,
      "source": "CLDR"
    },
    {
      "name": "Tamanipurit",
      "bcp_47_code": "kab",
      "is_canonical": true,
      "source": "CLDR"
    },
    {
      "name": "mỹnĩpuri",
      "bcp_47_code": "kgp",
      "is_canonical": true,
      "source": "CLDR"
    },
    {
      "name": "манипури тілі",
      "bcp_47_code": "kk",
      "iso_15924_code": "cyrl",
      "is_canonical": true,
      "source": "CLDR"
    },
    {
      "name": "ម៉ានីពូរី",
      "bcp_47_code": "km",
      "is_canonical": true,
      "source": "CLDR"
    },
    {
      "name": "ಮಣಿಪುರಿ",
      "bcp_47_code": "kn",
      "is_canonical": true,
      "source": "CLDR"
    },
    {
      "name": "마니푸리어",
      "bcp_47_code": "ko",
      "is_canonical": true,
      "source": "CLDR"
    },
    {
      "name": "मणिपुरी",
      "bcp_47_code": "kok",
      "is_canonical": true,
      "source": "CLDR"
    },
    {
      "name": "مَنیپوٗری",
      "bcp_47_code": "ks",
      "is_canonical": true,
      "source": "CLDR"
    },
    {
      "name": "Meitei-Manipuhresch",
      "bcp_47_code": "ksh",
      "is_canonical": true,
      "source": "CLDR"
    },
    {
      "name": "манипуриче",
      "bcp_47_code": "ky",
      "is_canonical": true,
      "source": "CLDR"
    },
    {
      "name": "meithei-Sprooch",
      "bcp_47_code": "lb",
      "is_canonical": true,
      "source": "CLDR"
    },
    {
      "name": "manipuri",
      "bcp_47_code": "lij",
      "is_canonical": true,
      "source": "CLDR"
    },
    {
      "name": "Namipuri Iyápi",
      "bcp_47_code": "lkt",
      "is_canonical": true,
      "source": "CLDR"
    },
    {
      "name": "ມານີພູຣິ",
      "bcp_47_code": "lo",
      "is_canonical": true,
      "source": "CLDR"
    },
    {
      "name": "manipurių",
      "bcp_47_code": "lt",
      "is_canonical": true,
      "source": "CLDR"
    },
    {
      "name": "manipūru",
      "bcp_47_code": "lv",
      "is_canonical": true,
      "source": "CLDR"
    },
    {
      "name": "मणिपुरी",
      "bcp_47_code": "mai",
      "is_canonical": true,
      "source": "CLDR"
    },
    {
      "name": "Manipuri",
      "bcp_47_code": "mi",
      "is_canonical": true,
      "source": "CLDR"
    },
    {
      "name": "манипурски",
      "bcp_47_code": "mk",
      "is_canonical": true,
      "source": "CLDR"
    },
    {
      "name": "മണിപ്പൂരി",
      "bcp_47_code": "ml",
      "is_canonical": true,
      "source": "CLDR"
    },
    {
      "name": "манипури",
      "bcp_47_code": "mn",
      "iso_15924_code": "cyrl",
      "is_canonical": true,
      "source": "CLDR"
    },
    {
      "name": "মৈতৈলোন্",
      "bcp_47_code": "mni",
      "source": "CLDR"
    },
    {
      "name": "मणिपुरी",
      "bcp_47_code": "mr",
      "is_canonical": true,
      "source": "CLDR"
    },
    {
      "name": "Manipuri",
      "bcp_47_code": "ms",
      "is_canonical": true,
      "source": "CLDR"
    },
    {
      "name": "Manipuri",
      "bcp_47_code": "mt",
      "is_canonical": true,
      "source": "CLDR"
    },
    {
      "name": "မနိပူရ",
      "bcp_47_code": "my",
      "is_canonical": true,
      "source": "CLDR"
    },
    {
      "name": "Manipuri",
      "bcp_47_code": "nds",
      "is_canonical": true,
      "source": "CLDR"
    },
    {
      "name": "मनिपुरी",
      "bcp_47_code": "ne",
      "is_canonical": true,
      "source": "CLDR"
    },
    {
      "name": "Meitei",
      "bcp_47_code": "nl",
      "is_canonical": true,
      "source": "CLDR"
    },
    {
      "name": "manipuri",
      "bcp_47_code": "no",
      "is_canonical": true,
      "source": "CLDR"
    },
    {
      "name": "ߡߊߣߌߔߎߙߌߞߊ߲",
      "bcp_47_code": "nqo",
      "is_canonical": true,
      "source": "CLDR"
    },
    {
      "name": "ମଣିପୁରୀ",
      "bcp_47_code": "or",
      "is_canonical": true,
      "source": "CLDR"
    },
    {
      "name": "ਮਨੀਪੁਰੀ",
      "bcp_47_code": "pa",
      "iso_15924_code": "guru",
      "is_canonical": true,
      "source": "CLDR"
    },
    {
      "name": "Manípuri",
      "bcp_47_code": "pcm",
      "is_canonical": true,
      "source": "CLDR"
    },
    {
      "name": "manipuri",
      "bcp_47_code": "pl",
      "is_canonical": true,
      "source": "CLDR"
    },
    {
      "name": "مانی پوری",
      "bcp_47_code": "ps",
      "is_canonical": true,
      "source": "CLDR"
    },
    {
      "name": "manipuri",
      "bcp_47_code": "pt",
      "is_canonical": true,
      "source": "CLDR"
    },
    {
      "name": "Manipuri Simi",
      "bcp_47_code": "qu",
      "is_canonical": true,
      "source": "CLDR"
    },
    {
      "name": "manipuri",
      "bcp_47_code": "rm",
      "is_canonical": true,
      "source": "CLDR"
    },
    {
      "name": "manipuri",
      "bcp_47_code": "ro",
      "is_canonical": true,
      "source": "CLDR"
    },
    {
      "name": "манипурский",
      "bcp_47_code": "ru",
      "is_canonical": true,
      "source": "CLDR"
    },
    {
      "name": "ᱢᱟᱹᱱᱤᱯᱩᱨᱤ",
      "bcp_47_code": "sat",
      "is_canonical": true,
      "source": "CLDR"
    },
    {
      "name": "manipuri",
      "bcp_47_code": "sc",
      "is_canonical": true,
      "source": "CLDR"
    },
    {
      "name": "ماني پوري",
      "bcp_47_code": "sd",
      "iso_15924_code": "arab",
      "is_canonical": true,
      "source": "CLDR"
    },
    {
      "name": "මනිපුරි",
      "bcp_47_code": "si",
      "is_canonical": true,
      "source": "CLDR"
    },
    {
      "name": "manípurčina",
      "bcp_47_code": "sk",
      "is_canonical": true,
      "source": "CLDR"
    },
    {
      "name": "manipurščina",
      "bcp_47_code": "sl",
      "is_canonical": true,
      "source": "CLDR"
    },
    {
      "name": "manipuri",
      "bcp_47_code": "smn",
      "is_canonical": true,
      "source": "CLDR"
    },
    {
      "name": "Maniburi",
      "bcp_47_code": "so",
      "is_canonical": true,
      "source": "CLDR"
    },
    {
      "name": "manipurisht",
      "bcp_47_code": "sq",
      "is_canonical": true,
      "source": "CLDR"
    },
    {
      "name": "манипурски",
      "bcp_47_code": "sr",
      "iso_15924_code": "cyrl",
      "is_canonical": true,
      "source": "CLDR"
    },
    {
      "name": "manipuri",
      "bcp_47_code": "sv",
      "is_canonical": true,
      "source": "CLDR"
    },
    {
      "name": "Kimanipuri",
      "bcp_47_code": "sw",
      "is_canonical": true,
      "source": "CLDR"
    },
    {
      "name": "மணிப்புரி",
      "bcp_47_code": "ta",
      "is_canonical": true,
      "source": "CLDR"
    },
    {
      "name": "మణిపురి",
      "bcp_47_code": "te",
      "is_canonical": true,
      "source": "CLDR"
    },
    {
      "name": "манипурӣ",
      "bcp_47_code": "tg",
      "is_canonical": true,
      "source": "CLDR"
    },
    {
      "name": "มณีปุระ",
      "bcp_47_code": "th",
      "is_canonical": true,
      "source": "CLDR"
    },
    {
      "name": "ማኒፑሪ",
      "bcp_47_code": "ti",
      "is_canonical": true,
      "source": "CLDR"
    },
    {
      "name": "manipuri dili",
      "bcp_47_code": "tk",
      "is_canonical": true,
      "source": "CLDR"
    },
    {
      "name": "lea fakamanipuli",
      "bcp_47_code": "to",
      "is_canonical": true,
      "source": "CLDR"
    },
    {
      "name": "Manipuri dili",
      "bcp_47_code": "tr",
      "is_canonical": true,
      "source": "CLDR"
    },
    {
      "name": "манипури",
      "bcp_47_code": "tt",
      "is_canonical": true,
      "source": "CLDR"
    },
    {
      "name": "مانىپۇرچە",
      "bcp_47_code": "ug",
      "is_canonical": true,
      "source": "CLDR"
    },
    {
      "name": "маніпурі",
      "bcp_47_code": "uk",
      "is_canonical": true,
      "source": "CLDR"
    },
    {
      "name": "منی پوری",
      "bcp_47_code": "ur",
      "is_canonical": true,
      "source": "CLDR"
    },
    {
      "name": "manipur",
      "bcp_47_code": "uz",
      "is_canonical": true,
      "source": "CLDR"
    },
    {
      "name": "tiếng Manipuri",
      "bcp_47_code": "vi",
      "is_canonical": true,
      "source": "CLDR"
    },
    {
      "name": "Manipuri",
      "bcp_47_code": "wo",
      "is_canonical": true,
      "source": "CLDR"
    },
    {
      "name": "Èdè Manipuri",
      "bcp_47_code": "yo",
      "is_canonical": true,
      "source": "CLDR"
    },
    {
      "name": "manipuri",
      "bcp_47_code": "yrl",
      "is_canonical": true,
      "source": "CLDR"
    },
    {
      "name": "曼尼普裡文",
      "bcp_47_code": "yue",
      "is_canonical": true,
      "source": "CLDR"
    },
    {
      "name": "曼尼普尔语",
      "bcp_47_code": "cmn",
      "is_canonical": true,
      "source": "CLDR"
    },
    {
      "name": "isi-Manipuri",
      "bcp_47_code": "zu",
      "is_canonical": true,
      "source": "CLDR"
    },
    {
      "name": "Manipoeri",
      "bcp_47_code": "af",
      "source": "GOOGLE_RESEARCH"
    },
    {
      "name": "মণিপুৰি",
      "bcp_47_code": "as",
      "source": "GOOGLE_RESEARCH"
    },
    {
      "name": "Manipuri dili",
      "bcp_47_code": "az",
      "iso_15924_code": "latn",
      "source": "GOOGLE_RESEARCH"
    },
    {
      "name": "маніпуры",
      "bcp_47_code": "be",
      "source": "GOOGLE_RESEARCH"
    },
    {
      "name": "манипури",
      "bcp_47_code": "bg",
      "source": "GOOGLE_RESEARCH"
    },
    {
      "name": "manipuri",
      "bcp_47_code": "ca",
      "source": "GOOGLE_RESEARCH"
    },
    {
      "name": "Manipuri",
      "bcp_47_code": "de",
      "source": "GOOGLE_RESEARCH"
    },
    {
      "name": "Manipuri",
      "bcp_47_code": "gl",
      "source": "GOOGLE_RESEARCH"
    },
    {
      "name": "Manipuri",
      "bcp_47_code": "gsw",
      "source": "GOOGLE_RESEARCH"
    },
    {
      "name": "manipuri",
      "bcp_47_code": "hr",
      "source": "GOOGLE_RESEARCH"
    },
    {
      "name": "Manipuri",
      "bcp_47_code": "in",
      "is_canonical": true,
      "source": "GOOGLE_RESEARCH"
    },
    {
      "name": "manipuri",
      "bcp_47_code": "is",
      "source": "GOOGLE_RESEARCH"
    },
    {
      "name": "Манипури",
      "bcp_47_code": "kk",
      "iso_15924_code": "cyrl",
      "source": "GOOGLE_RESEARCH"
    },
    {
      "name": "Манипуриче",
      "bcp_47_code": "ky",
      "source": "GOOGLE_RESEARCH"
    },
    {
      "name": "Manipuri",
      "bcp_47_code": "ln",
      "is_canonical": true,
      "source": "GOOGLE_RESEARCH"
    },
    {
      "name": "Manipuri",
      "bcp_47_code": "lo",
      "source": "GOOGLE_RESEARCH"
    },
    {
      "name": "Манипури",
      "bcp_47_code": "mn",
      "iso_15924_code": "cyrl",
      "source": "GOOGLE_RESEARCH"
    },
    {
      "name": "Manipuri",
      "bcp_47_code": "mo",
      "is_canonical": true,
      "source": "GOOGLE_RESEARCH"
    },
    {
      "name": "မဏိပူရီ",
      "bcp_47_code": "my",
      "source": "GOOGLE_RESEARCH"
    },
    {
      "name": "manipuri",
      "bcp_47_code": "nb",
      "is_canonical": true,
      "source": "GOOGLE_RESEARCH"
    },
    {
      "name": "मणिपुरी",
      "bcp_47_code": "ne",
      "source": "GOOGLE_RESEARCH"
    },
    {
      "name": "Manipuri",
      "bcp_47_code": "nl",
      "source": "GOOGLE_RESEARCH"
    },
    {
      "name": "ਮਣੀਪੁਰੀ",
      "bcp_47_code": "pa",
      "iso_15924_code": "guru",
      "source": "GOOGLE_RESEARCH"
    },
    {
      "name": "манипури",
      "bcp_47_code": "ru",
      "source": "GOOGLE_RESEARCH"
    },
    {
      "name": "Manipurčina",
      "bcp_47_code": "sk",
      "source": "GOOGLE_RESEARCH"
    },
    {
      "name": "Manipurisht",
      "bcp_47_code": "sq",
      "source": "GOOGLE_RESEARCH"
    },
    {
      "name": "манипури",
      "bcp_47_code": "sr",
      "iso_15924_code": "cyrl",
      "source": "GOOGLE_RESEARCH"
    },
    {
      "name": "மணிப்பூரி",
      "bcp_47_code": "ta",
      "source": "GOOGLE_RESEARCH"
    },
    {
      "name": "ภาษามณีปุระ",
      "bcp_47_code": "th",
      "source": "GOOGLE_RESEARCH"
    },
    {
      "name": "Manipuri",
      "bcp_47_code": "tl",
      "is_canonical": true,
      "source": "GOOGLE_RESEARCH"
    },
    {
      "name": "Manipuri",
      "bcp_47_code": "tr",
      "source": "GOOGLE_RESEARCH"
    },
    {
      "name": "tiếng Manipur",
      "bcp_47_code": "vi",
      "source": "GOOGLE_RESEARCH"
    },
    {
      "name": "i-Manipuri",
      "bcp_47_code": "zu",
      "source": "GOOGLE_RESEARCH"
    },
    {
      "name": "Lenga Meitei",
      "bcp_47_code": "pms",
      "is_canonical": true,
      "source": "WIKIDATA"
    },
    {
      "name": "język manipuri",
      "bcp_47_code": "pl",
      "source": "WIKIDATA"
    },
    {
      "name": "마니푸르어",
      "bcp_47_code": "ko",
      "source": "WIKIDATA"
    },
    {
      "name": "meitei",
      "bcp_47_code": "fr",
      "source": "WIKIDATA"
    },
    {
      "name": "meitei",
      "bcp_47_code": "es",
      "source": "WIKIDATA"
    },
    {
      "name": "மணிப்புரியம்",
      "bcp_47_code": "ta",
      "source": "WIKIDATA"
    },
    {
      "name": "ମଇତେଇ ଭାଷା",
      "bcp_47_code": "or",
      "source": "WIKIDATA"
    },
    {
      "name": "Meitei",
      "bcp_47_code": "de",
      "source": "WIKIDATA"
    },
    {
      "name": "bahasa Manipuri",
      "bcp_47_code": "id",
      "source": "WIKIDATA"
    },
    {
      "name": "মৈতৈ মণিপুরী ভাষা",
      "bcp_47_code": "bn",
      "source": "WIKIDATA"
    },
    {
      "name": "മണിപ്പൂരി ഭാഷ",
      "bcp_47_code": "ml",
      "source": "WIKIDATA"
    },
    {
      "name": "meiteieg",
      "bcp_47_code": "br",
      "source": "WIKIDATA"
    },
    {
      "name": "tiếng Meitei",
      "bcp_47_code": "vi",
      "source": "WIKIDATA"
    },
    {
      "name": "manipuri jezik",
      "bcp_47_code": "sh",
      "is_canonical": true,
      "source": "WIKIDATA"
    },
    {
      "name": "مائیتائی بولی",
      "bcp_47_code": "pnb",
      "is_canonical": true,
      "source": "WIKIDATA"
    },
    {
      "name": "meitei",
      "bcp_47_code": "sv",
      "source": "WIKIDATA"
    },
    {
      "name": "मणिपुरी भाषा",
      "bcp_47_code": "hi",
      "source": "WIKIDATA"
    },
    {
      "name": "língua manipuri",
      "bcp_47_code": "pt",
      "source": "WIKIDATA"
    },
    {
      "name": "manipura lingvo",
      "bcp_47_code": "eo",
      "source": "WIKIDATA"
    },
    {
      "name": "манипури језик",
      "bcp_47_code": "sr",
      "iso_15924_code": "cyrl",
      "source": "WIKIDATA"
    },
    {
      "name": "Meitei",
      "bcp_47_code": "en",
      "source": "WIKIDATA"
    },
    {
      "name": "lingua Meitei",
      "bcp_47_code": "la",
      "is_canonical": true,
      "source": "WIKIDATA"
    },
    {
      "name": "મણિપુરી ભાષા",
      "bcp_47_code": "gu",
      "source": "WIKIDATA"
    },
    {
      "name": "मणिपुरी भाषा",
      "bcp_47_code": "mr",
      "source": "WIKIDATA"
    },
    {
      "name": "Мэйтэй",
      "bcp_47_code": "kv",
      "is_canonical": true,
      "source": "WIKIDATA"
    },
    {
      "name": "मणिपुरी भाषा",
      "bcp_47_code": "ne",
      "source": "WIKIDATA"
    },
    {
      "name": "মেইতেই ঠার",
      "bcp_47_code": "bpy",
      "is_canonical": true,
      "source": "WIKIDATA"
    },
    {
      "name": "meitei-lon",
      "bcp_47_code": "nb",
      "source": "WIKIDATA"
    },
    {
      "name": "Meiteiskŏ gŏdka",
      "bcp_47_code": "szl",
      "is_canonical": true,
      "source": "WIKIDATA"
    },
    {
      "name": "manipurin kieli",
      "bcp_47_code": "fi",
      "source": "WIKIDATA"
    },
    {
      "name": "manipur tili",
      "bcp_47_code": "uz",
      "source": "WIKIDATA"
    },
    {
      "name": "زبان مانیپوری",
      "bcp_47_code": "fa",
      "source": "WIKIDATA"
    },
    {
      "name": "manipuri keel",
      "bcp_47_code": "et",
      "source": "WIKIDATA"
    },
    {
      "name": "მანიპური",
      "bcp_47_code": "xmf",
      "is_canonical": true,
      "source": "WIKIDATA"
    },
    {
      "name": "Meithei leid",
      "bcp_47_code": "sco",
      "is_canonical": true,
      "source": "WIKIDATA"
    },
    {
      "name": "манипурски јазик",
      "bcp_47_code": "mk",
      "source": "WIKIDATA"
    },
    {
      "name": "ਮੀਤੇਈ ਭਾਸ਼ਾ",
      "bcp_47_code": "pa",
      "iso_15924_code": "guru",
      "source": "WIKIDATA"
    },
    {
      "name": "Kimeitei",
      "bcp_47_code": "sw",
      "source": "WIKIDATA"
    },
    {
      "name": "Μέιτέι",
      "bcp_47_code": "el",
      "source": "WIKIDATA"
    },
    {
      "name": "मणिपुरी भाषा",
      "bcp_47_code": "bho",
      "is_canonical": true,
      "source": "WIKIDATA"
    },
    {
      "name": "মেইতেই ভাষা",
      "bcp_47_code": "as",
      "source": "WIKIDATA"
    },
    {
      "name": "idioma meitei",
      "bcp_47_code": "ast",
      "source": "WIKIDATA"
    },
    {
      "name": "ꯃꯤꯇꯩ ꯂꯣꯟ",
      "bcp_47_code": "mni",
      "source": "WIKIDATA"
    },
    {
      "name": "Meitei",
      "bcp_47_code": "af",
      "source": "WIKIDATA"
    },
    {
      "name": "మణిపురి భాష",
      "bcp_47_code": "te",
      "source": "WIKIDATA"
    },
    {
      "name": "manipūri",
      "bcp_47_code": "lt",
      "source": "WIKIDATA"
    },
    {
      "name": "ᱢᱮᱭᱛᱮᱭ ᱯᱟᱹᱨᱥᱤ",
      "bcp_47_code": "sat",
      "source": "WIKIDATA"
    },
    {
      "name": "منی پوری زبان",
      "bcp_47_code": "ur",
      "source": "WIKIDATA"
    },
    {
      "name": "lingua meitei",
      "bcp_47_code": "ia",
      "source": "WIKIDATA"
    },
    {
      "name": "曼尼普尔语",
      "bcp_47_code": "wuu",
      "is_canonical": true,
      "source": "WIKIDATA"
    },
    {
      "name": "Lingua meitei",
      "bcp_47_code": "gl",
      "source": "WIKIDATA"
    },
    {
      "name": "الميتية",
      "bcp_47_code": "ar",
      "source": "WIKIDATA"
    },
    {
      "name": "Манипури теле",
      "bcp_47_code": "tt",
      "source": "WIKIDATA"
    },
    {
      "name": "曼尼普爾文",
      "bcp_47_code": "yue",
      "source": "WIKIDATA"
    },
    {
      "name": "曼尼普爾語",
      "bcp_47_code": "cmn",
      "source": "WIKIDATA"
    },
    {
      "name": "ميئتي ٻولي",
      "bcp_47_code": "sd",
      "iso_15924_code": "arab",
      "source": "WIKIDATA"
    },
    {
      "name": "manipuri",
      "bcp_47_code": "vec",
      "is_canonical": true,
      "source": "WIKIDATA"
    },
    {
      "name": "मणिपुरीभाषा",
      "bcp_47_code": "sa",
      "is_canonical": true,
      "source": "WIKIDATA"
    },
    {
      "name": "ကသည်းဘာသာစကား",
      "bcp_47_code": "my",
      "source": "WIKIDATA"
    },
    {
      "name": "ꠝꠘꠤꠙꠥꠞꠤ",
      "bcp_47_code": "syl",
      "is_canonical": true,
      "source": "WIKIDATA"
    },
    {
      "name": "मणिपुरी भाषा",
      "bcp_47_code": "anp",
      "is_canonical": true,
      "source": "WIKIDATA"
    },
    {
      "name": "ភាសាមណីបុរៈ",
      "bcp_47_code": "km",
      "source": "WIKIDATA"
    },
    {
      "name": "Meitei dili",
      "bcp_47_code": "tr",
      "source": "WIKIDATA"
    },
    {
      "name": "曼尼浦尔语",
      "bcp_47_code": "cmn",
      "source": "WIKIDATA"
    },
    {
      "name": "梅泰语",
      "bcp_47_code": "cmn",
      "source": "WIKIDATA"
    },
    {
      "name": "마니푸르 어",
      "bcp_47_code": "ko",
      "source": "WIKIDATA"
    },
    {
      "name": "metei",
      "bcp_47_code": "fr",
      "source": "WIKIDATA"
    },
    {
      "name": "manipurî",
      "bcp_47_code": "fr",
      "source": "WIKIDATA"
    },
    {
      "name": "manipourî",
      "bcp_47_code": "fr",
      "source": "WIKIDATA"
    },
    {
      "name": "manipouri",
      "bcp_47_code": "fr",
      "source": "WIKIDATA"
    },
    {
      "name": "idioma manipurí",
      "bcp_47_code": "es",
      "source": "WIKIDATA"
    },
    {
      "name": "idioma manipuri",
      "bcp_47_code": "es",
      "source": "WIKIDATA"
    },
    {
      "name": "மெய்ட்டேய்",
      "bcp_47_code": "ta",
      "source": "WIKIDATA"
    },
    {
      "name": "bahasa Meitei",
      "bcp_47_code": "id",
      "source": "WIKIDATA"
    },
    {
      "name": "মৈতৈ",
      "bcp_47_code": "bn",
      "source": "WIKIDATA"
    },
    {
      "name": "মেইতেই ভাষা",
      "bcp_47_code": "bn",
      "source": "WIKIDATA"
    },
    {
      "name": "মণিপুরি ভাষা",
      "bcp_47_code": "bn",
      "source": "WIKIDATA"
    },
    {
      "name": "মণিপুরী ভাষা",
      "bcp_47_code": "bn",
      "source": "WIKIDATA"
    },
    {
      "name": "メイテイ語",
      "bcp_47_code": "ja",
      "source": "WIKIDATA"
    },
    {
      "name": "マニプル語",
      "bcp_47_code": "ja",
      "source": "WIKIDATA"
    },
    {
      "name": "マニプール語",
      "bcp_47_code": "ja",
      "source": "WIKIDATA"
    },
    {
      "name": "マニプリー語",
      "bcp_47_code": "ja",
      "source": "WIKIDATA"
    },
    {
      "name": "manipoureg",
      "bcp_47_code": "br",
      "source": "WIKIDATA"
    },
    {
      "name": "meiteiek",
      "bcp_47_code": "br",
      "source": "WIKIDATA"
    },
    {
      "name": "meitei jezik",
      "bcp_47_code": "sh",
      "source": "WIKIDATA"
    },
    {
      "name": "meiteilon",
      "bcp_47_code": "sv",
      "source": "WIKIDATA"
    },
    {
      "name": "manipure",
      "bcp_47_code": "eo",
      "source": "WIKIDATA"
    },
    {
      "name": "manipuroj",
      "bcp_47_code": "eo",
      "source": "WIKIDATA"
    },
    {
      "name": "манипурский язык",
      "bcp_47_code": "ru",
      "source": "WIKIDATA"
    },
    {
      "name": "мейтей",
      "bcp_47_code": "ru",
      "source": "WIKIDATA"
    },
    {
      "name": "мейтхей",
      "bcp_47_code": "ru",
      "source": "WIKIDATA"
    },
    {
      "name": "ภาษามณีปุริ",
      "bcp_47_code": "th",
      "source": "WIKIDATA"
    },
    {
      "name": "ภาษาเมยเทย",
      "bcp_47_code": "th",
      "source": "WIKIDATA"
    },
    {
      "name": "ภาษาไมไต",
      "bcp_47_code": "th",
      "source": "WIKIDATA"
    },
    {
      "name": "ภาษาเมเธ",
      "bcp_47_code": "th",
      "source": "WIKIDATA"
    },
    {
      "name": "ภาษาเมเท",
      "bcp_47_code": "th",
      "source": "WIKIDATA"
    },
    {
      "name": "มณีปุรี",
      "bcp_47_code": "th",
      "source": "WIKIDATA"
    },
    {
      "name": "мейтей",
      "bcp_47_code": "uk",
      "source": "WIKIDATA"
    },
    {
      "name": "Манипури",
      "bcp_47_code": "kv",
      "source": "WIKIDATA"
    },
    {
      "name": "мејтејски јазик",
      "bcp_47_code": "mk",
      "source": "WIKIDATA"
    },
    {
      "name": "мејтеј",
      "bcp_47_code": "mk",
      "source": "WIKIDATA"
    },
    {
      "name": "манипури",
      "bcp_47_code": "mk",
      "source": "WIKIDATA"
    },
    {
      "name": "Μεϊτέι",
      "bcp_47_code": "el",
      "source": "WIKIDATA"
    },
    {
      "name": "lingua manipuri",
      "bcp_47_code": "it",
      "source": "WIKIDATA"
    },
    {
      "name": "meitei-lon",
      "bcp_47_code": "it",
      "source": "WIKIDATA"
    },
    {
      "name": "meitei-lol",
      "bcp_47_code": "it",
      "source": "WIKIDATA"
    },
    {
      "name": "meitei",
      "bcp_47_code": "it",
      "source": "WIKIDATA"
    },
    {
      "name": "Meitei-Lon",
      "bcp_47_code": "en",
      "source": "WIKIDATA"
    },
    {
      "name": "Meithei",
      "bcp_47_code": "en",
      "source": "WIKIDATA"
    },
    {
      "name": "Meetei",
      "bcp_47_code": "en",
      "source": "WIKIDATA"
    },
    {
      "name": "Meiteilon",
      "bcp_47_code": "en",
      "source": "WIKIDATA"
    },
    {
      "name": "Meetei-Lon",
      "bcp_47_code": "en",
      "source": "WIKIDATA"
    },
    {
      "name": "Kanglei-Lon",
      "bcp_47_code": "en",
      "source": "WIKIDATA"
    },
    {
      "name": "Meetei Manipuri",
      "bcp_47_code": "en",
      "source": "WIKIDATA"
    },
    {
      "name": "মণিপুৰী ভাষা",
      "bcp_47_code": "as",
      "source": "WIKIDATA"
    },
    {
      "name": "মেইতেই লোল্",
      "bcp_47_code": "as",
      "source": "WIKIDATA"
    },
    {
      "name": "পাংগাল-লোল",
      "bcp_47_code": "as",
      "source": "WIKIDATA"
    },
    {
      "name": "মৈতৈ ভাষা",
      "bcp_47_code": "as",
      "source": "WIKIDATA"
    },
    {
      "name": "meitei",
      "bcp_47_code": "ca",
      "source": "WIKIDATA"
    },
    {
      "name": "मेइतेई",
      "bcp_47_code": "bho",
      "source": "WIKIDATA"
    },
    {
      "name": "ꯀꯪꯂꯩꯂꯣꯟ",
      "bcp_47_code": "mni",
      "source": "WIKIDATA"
    },
    {
      "name": "اللغة الميتية",
      "bcp_47_code": "ar",
      "source": "WIKIDATA"
    },
    {
      "name": "لغة ميتية",
      "bcp_47_code": "ar",
      "source": "WIKIDATA"
    },
    {
      "name": "मणिपुरी भाषा",
      "bcp_47_code": "sa",
      "source": "WIKIDATA"
    },
    {
      "name": "मेइतेइ",
      "bcp_47_code": "sa",
      "source": "WIKIDATA"
    },
    {
      "name": "मेइथेइलॊन्",
      "bcp_47_code": "sa",
      "source": "WIKIDATA"
    },
    {
      "name": "मेइथेइलोन",
      "bcp_47_code": "sa",
      "source": "WIKIDATA"
    },
    {
      "name": "मीतेइलॊन्",
      "bcp_47_code": "sa",
      "source": "WIKIDATA"
    },
    {
      "name": "मेइतेइ",
      "bcp_47_code": "hi",
      "source": "WIKIDATA"
    },
    {
      "name": "ਮਨੀ",
      "bcp_47_code": "pa",
      "iso_15924_code": "guru",
      "source": "WIKIDATA"
    },
    {
      "name": "ꠝꠘꠤ ꠙꠥꠞꠤ ꠝꠣꠔ",
      "bcp_47_code": "syl",
      "source": "WIKIDATA"
    },
    {
      "name": "idioma meitei",
      "bcp_47_code": "es",
      "source": "LEXVO"
    },
    {
      "name": "মৈতৈ ভাষা",
      "bcp_47_code": "bn",
      "source": "LEXVO"
    },
    {
      "name": "ภาษามณีปุรี",
      "bcp_47_code": "th",
      "source": "LEXVO"
    },
    {
      "name": "Meitheiron",
      "bcp_47_code": "mni",
      "is_canonical": true,
      "source": "GOOGLE_RESEARCH"
    },
    {
      "name": "ꯃꯩꯇꯩꯂꯣꯟ",
      "bcp_47_code": "mni",
      "source": "GOOGLE_RESEARCH"
    },
    {
      "name": "Meiteilon (Manipuri)",
      "bcp_47_code": "en",
      "is_canonical": true,
      "source": "ISO_639"
    }
  ],
  "language_script_locale": [
    {
      "script": {
        "iso_15924_code": "beng",
        "is_canonical": true,
        "source": "GOOGLE_RESEARCH"
      },
      "locale": {
        "iso_3166_code": "in",
        "source": "GOOGLE_RESEARCH"
      },
      "speaker_data": {
        "number_of_speakers": 1500000,
        "source": "CLDR"
      },
      "geolocation": {
        "latitude": 24.4409,
        "longitude": 93.3426,
        "source": "GLOTTOLOG"
      }
    },
    {
      "script": {
        "iso_15924_code": "latn",
        "is_for_transliteration": true,
        "source": "GOOGLE_RESEARCH"
      },
      "locale": {
        "iso_3166_code": "in",
        "source": "GOOGLE_RESEARCH"
      },
      "speaker_data": {
        "number_of_speakers": 1500000,
        "source": "CLDR"
      },
      "geolocation": {
        "latitude": 24.4409,
        "longitude": 93.3426,
        "source": "GOOGLE_RESEARCH"
      }
    },
    {
      "script": {
        "iso_15924_code": "mtei",
        "has_official_status": true,
        "source": "GOOGLE_RESEARCH"
      },
      "locale": {
        "iso_3166_code": "in",
        "source": "GOOGLE_RESEARCH"
      },
      "speaker_data": {
        "number_of_speakers": 1500000,
        "source": "CLDR"
      },
      "geolocation": {
        "latitude": 24.4409,
        "longitude": 93.3426,
        "source": "GOOGLE_RESEARCH"
      }
    }
  ]
}