{
  "bcp_47_code": "nbo",
  "iso_639_3_code": "nbo",
  "glottocode": "nkuk1238",
  "wikidata_id": "Q3914482",
  "total_population": 10000,
  "language_scope": {
    "scope": "LANGUAGE",
    "source": "ISO_639"
  },
  "name_data": [
    {
      "name": "Nkukoli",
      "bcp_47_code": "en",
      "is_canonical": true,
      "source": "ISO_639"
    },
    {
      "name": "Kinkukoli",
      "bcp_47_code": "sw",
      "is_canonical": true,
      "source": "WIKIDATA"
    },
    {
      "name": "Lenga Nkukoli",
      "bcp_47_code": "pms",
      "is_canonical": true,
      "source": "WIKIDATA"
    },
    {
      "name": "nkukoli",
      "bcp_47_code": "ca",
      "is_canonical": true,
      "source": "WIKIDATA"
    },
    {
      "name": "Nkukoli",
      "bcp_47_code": "ig",
      "is_canonical": true,
      "source": "WIKIDATA"
    },
    {
      "name": "Asụsụ Nkukoli",
      "bcp_47_code": "ig",
      "source": "WIKIDATA"
    }
  ],
  "language_script_locale": [
    {
      "script": {
        "iso_15924_code": "latn",
        "is_canonical": true,
        "source": "WIKTIONARY"
      },
      "locale": {
        "iso_3166_code": "ng",
        "source": "GLOTTOLOG"
      },
      "speaker_data": {
        "number_of_speakers": 10000,
        "source": "WIKIPEDIA"
      },
      "geolocation": {
        "latitude": 5.7562,
        "longitude": 8.28051,
        "source": "GLOTTOLOG"
      }
    }
  ]
}