{
  "bcp_47_code": "niw",
  "iso_639_3_code": "niw",
  "glottocode": "nimo1247",
  "wikidata_id": "Q3504126",
  "total_population": 350,
  "language_scope": {
    "scope": "LANGUAGE",
    "source": "ISO_639"
  },
  "language_description": {
    "description": "language of New Guinea",
    "source": "WIKIDATA"
  },
  "name_data": [
    {
      "name": "Nimo",
      "bcp_47_code": "en",
      "is_canonical": true,
      "source": "ISO_639"
    },
    {
      "name": "Lenga nimo",
      "bcp_47_code": "pms",
      "is_canonical": true,
      "source": "WIKIDATA"
    },
    {
      "name": "nimo jezik",
      "bcp_47_code": "hr",
      "is_canonical": true,
      "source": "WIKIDATA"
    },
    {
      "name": "nimoeg",
      "bcp_47_code": "br",
      "is_canonical": true,
      "source": "WIKIDATA"
    },
    {
      "name": "nimo",
      "bcp_47_code": "fr",
      "is_canonical": true,
      "source": "WIKIDATA"
    },
    {
      "name": "Kinimo",
      "bcp_47_code": "sw",
      "is_canonical": true,
      "source": "WIKIDATA"
    },
    {
      "name": "język nimo",
      "bcp_47_code": "pl",
      "is_canonical": true,
      "source": "WIKIDATA"
    },
    {
      "name": "Nimo",
      "bcp_47_code": "ilo",
      "is_canonical": true,
      "source": "WIKIDATA"
    }
  ],
  "language_script_locale": [
    {
      "script": {
        "iso_15924_code": "latn",
        "is_canonical": true,
        "source": "ASSUMED_BASED_ON_LOCALE"
      },
      "locale": {
        "iso_3166_code": "pg",
        "source": "GLOTTOLOG"
      },
      "speaker_data": {
        "number_of_speakers": 350,
        "source": "WIKIPEDIA"
      },
      "geolocation": {
        "latitude": -4.3582,
        "longitude": 141.578,
        "source": "GLOTTOLOG"
      }
    }
  ]
}