{
  "bcp_47_code": "txm",
  "iso_639_3_code": "txm",
  "glottocode": "tomi1243",
  "wikidata_id": "Q7818911",
  "total_population": 30000,
  "language_scope": {
    "scope": "LANGUAGE",
    "source": "ISO_639"
  },
  "name_data": [
    {
      "name": "Tomini",
      "bcp_47_code": "en",
      "is_canonical": true,
      "source": "ISO_639"
    },
    {
      "name": "Lenga tomini",
      "bcp_47_code": "pms",
      "is_canonical": true,
      "source": "WIKIDATA"
    },
    {
      "name": "Tomini",
      "bcp_47_code": "de",
      "is_canonical": true,
      "source": "WIKIDATA"
    },
    {
      "name": "Kitomini",
      "bcp_47_code": "sw",
      "is_canonical": true,
      "source": "WIKIDATA"
    },
    {
      "name": "Tomini",
      "bcp_47_code": "ilo",
      "is_canonical": true,
      "source": "WIKIDATA"
    },
    {
      "name": "Wikang Tomini",
      "bcp_47_code": "tl",
      "is_canonical": true,
      "source": "WIKIDATA"
    },
    {
      "name": "tomini",
      "bcp_47_code": "fr",
      "is_canonical": true,
      "source": "WIKIDATA"
    },
    {
      "name": "język tomini",
      "bcp_47_code": "pl",
      "is_canonical": true,
      "source": "WIKIDATA"
    },
    {
      "name": "Tataramon na Tomini",
      "bcp_47_code": "bcl",
      "is_canonical": true,
      "source": "WIKIDATA"
    }
  ],
  "language_script_locale": [
    {
      "script": {
        "iso_15924_code": "xxxx",
        "is_canonical": true,
        "source": "SOURCE_UNSPECIFIED"
      },
      "locale": {
        "iso_3166_code": "id",
        "source": "GLOTTOLOG"
      },
      "speaker_data": {
        "number_of_speakers": 30000,
        "source": "WIKIPEDIA"
      }
    }
  ]
}